{"version": "", "flags": {}, "shapes": [{"label": "1056817", "points": [[212, 332], [720, 371], [723, 1281], [174, 1276]], "group_id": null, "shape_type": "polygon", "flags": {}}, {"label": "1056817", "points": [[198, 1281], [723, 1279], [720, 2208], [203, 2249]], "group_id": null, "shape_type": "polygon", "flags": {}}, {"label": "1056824", "points": [[230, 348], [718, 387], [720, 533], [222, 518]], "group_id": null, "shape_type": "polygon", "flags": {}}, {"label": "1056824", "points": [[226, 541], [711, 555], [713, 746], [223, 747]], "group_id": null, "shape_type": "polygon", "flags": {}}, {"label": "1056824", "points": [[220, 771], [716, 767], [716, 956], [214, 991]], "group_id": null, "shape_type": "polygon", "flags": {}}, {"label": "1056824", "points": [[214, 1013], [716, 979], [716, 1165], [205, 1218]], "group_id": null, "shape_type": "polygon", "flags": {}}, {"label": "1056824", "points": [[230, 1351], [718, 1372], [721, 1592], [228, 1566]], "group_id": null, "shape_type": "polygon", "flags": {}}, {"label": "1056824", "points": [[226, 1585], [716, 1616], [716, 1807], [224, 1797]], "group_id": null, "shape_type": "polygon", "flags": {}}, {"label": "1056824", "points": [[230, 1824], [714, 1830], [716, 1997], [229, 2018]], "group_id": null, "shape_type": "polygon", "flags": {}}, {"label": "1056824", "points": [[231, 2040], [715, 2023], [720, 2199], [228, 2235]], "group_id": null, "shape_type": "polygon", "flags": {}}], "imagePath": "1148a64ed593320561162893e44ff0cc.jpg", "imageData": null, "imageHeight": 2560, "imageWidth": 720}