{"version": "", "flags": {}, "shapes": [{"label": "1033458", "points": [[325, 693], [316, 1005], [1100, 961], [1105, 724]], "group_id": null, "shape_type": "polygon", "flags": {}}, {"label": "1033459", "points": [[314, 1046], [310, 1399], [1101, 1274], [1100, 1002]], "group_id": null, "shape_type": "polygon", "flags": {}}, {"label": "1033462", "points": [[318, 1437], [318, 1544], [1108, 1548], [1104, 1309]], "group_id": null, "shape_type": "polygon", "flags": {}}, {"label": "1033458", "points": [[420, 1745], [1138, 1854], [1147, 1634], [771, 1552], [437, 1542]], "group_id": null, "shape_type": "polygon", "flags": {}}, {"label": "1033459", "points": [[419, 1771], [396, 2078], [1132, 2153], [1141, 1877]], "group_id": null, "shape_type": "polygon", "flags": {}}, {"label": "1033462", "points": [[388, 2105], [370, 2420], [1123, 2449], [1131, 2173]], "group_id": null, "shape_type": "polygon", "flags": {}}], "imagePath": "14eb478c60287b6f881d0bc3d0180add.jpg", "imageData": null, "imageHeight": 3100, "imageWidth": 1230}