{"version": "", "flags": {}, "shapes": [{"label": "1033458", "points": [[509, 686], [1185, 688], [1180, 945], [504, 890]], "group_id": null, "shape_type": "polygon", "flags": {}}, {"label": "1033459", "points": [[494, 943], [1180, 1029], [1178, 1151], [492, 1075]], "group_id": null, "shape_type": "polygon", "flags": {}}, {"label": "1033462", "points": [[499, 1122], [1175, 1226], [1168, 1482], [492, 1331]], "group_id": null, "shape_type": "polygon", "flags": {}}, {"label": "1033458", "points": [[510, 1568], [503, 1781], [1189, 1644], [1194, 1546]], "group_id": null, "shape_type": "polygon", "flags": {}}, {"label": "1033459", "points": [[497, 1823], [1187, 1708], [1183, 1873], [490, 1969]], "group_id": null, "shape_type": "polygon", "flags": {}}, {"label": "1033462", "points": [[494, 2010], [1183, 1916], [1180, 2228], [490, 2238]], "group_id": null, "shape_type": "polygon", "flags": {}}], "imagePath": "169f3bb7bff22847bf9f7d1b3c0a3207.jpg", "imageData": null, "imageHeight": 3100, "imageWidth": 1230}