{"version": "", "flags": {}, "shapes": [{"label": "1056817", "points": [[292, 287], [240, 1544], [1181, 1549], [1178, 432]], "group_id": null, "shape_type": "polygon", "flags": {}}, {"label": "1056817", "points": [[338, 1552], [289, 3096], [1113, 3096], [1222, 3060], [1227, 1557]], "group_id": null, "shape_type": "polygon", "flags": {}}, {"label": "1056824", "points": [[342, 361], [1102, 462], [1102, 697], [324, 658]], "group_id": null, "shape_type": "polygon", "flags": {}}, {"label": "1056824", "points": [[313, 685], [1102, 724], [1102, 966], [305, 1017]], "group_id": null, "shape_type": "polygon", "flags": {}}, {"label": "1056824", "points": [[311, 1061], [1113, 995], [1107, 1292], [305, 1414]], "group_id": null, "shape_type": "polygon", "flags": {}}, {"label": "1056824", "points": [[374, 1546], [374, 1707], [1139, 1810], [1142, 1554]], "group_id": null, "shape_type": "polygon", "flags": {}}, {"label": "1056824", "points": [[377, 1727], [1139, 1834], [1139, 2115], [372, 2061]], "group_id": null, "shape_type": "polygon", "flags": {}}, {"label": "1056824", "points": [[359, 2084], [1150, 2141], [1155, 2413], [349, 2428]], "group_id": null, "shape_type": "polygon", "flags": {}}, {"label": "1056824", "points": [[338, 2462], [1188, 2439], [1191, 2708], [323, 2798]], "group_id": null, "shape_type": "polygon", "flags": {}}, {"label": "1056824", "points": [[328, 2832], [1189, 2740], [1201, 2910], [328, 3037]], "group_id": null, "shape_type": "polygon", "flags": {}}], "imagePath": "1a4c501ae80d804bf6432961c555c642.jpg", "imageData": null, "imageHeight": 3100, "imageWidth": 1230}