{"version": "", "flags": {}, "shapes": [{"label": "1033458", "points": [[408, 726], [1125, 729], [1119, 1010], [396, 1001]], "group_id": null, "shape_type": "polygon", "flags": {}}, {"label": "1033459", "points": [[419, 1042], [1144, 1060], [1141, 1198], [404, 1186]], "group_id": null, "shape_type": "polygon", "flags": {}}, {"label": "1033462", "points": [[396, 1220], [1146, 1235], [1137, 1478], [390, 1460]], "group_id": null, "shape_type": "polygon", "flags": {}}, {"label": "1033458", "points": [[405, 1595], [1107, 1577], [1116, 1835], [399, 1853]], "group_id": null, "shape_type": "polygon", "flags": {}}, {"label": "1033459", "points": [[410, 1887], [1120, 1875], [1114, 2016], [407, 2037]], "group_id": null, "shape_type": "polygon", "flags": {}}, {"label": "1033462", "points": [[411, 2057], [1119, 2036], [1125, 2267], [408, 2291]], "group_id": null, "shape_type": "polygon", "flags": {}}], "imagePath": "2015cb30c62abb2d1140c622dc33b0e8.jpg", "imageData": null, "imageHeight": 3100, "imageWidth": 1230}