{"version": "", "flags": {}, "shapes": [{"label": "1056817", "points": [[405, 345], [1227, 296], [1227, 1547], [414, 1547]], "group_id": null, "shape_type": "polygon", "flags": {}}, {"label": "1056817", "points": [[445, 1553], [1228, 1545], [1227, 2954], [426, 2832]], "group_id": null, "shape_type": "polygon", "flags": {}}, {"label": "1056824", "points": [[438, 399], [1186, 352], [1185, 692], [442, 699]], "group_id": null, "shape_type": "polygon", "flags": {}}, {"label": "1056824", "points": [[442, 725], [1179, 723], [1179, 864], [442, 853]], "group_id": null, "shape_type": "polygon", "flags": {}}, {"label": "1056824", "points": [[445, 880], [1176, 898], [1169, 1132], [444, 1087]], "group_id": null, "shape_type": "polygon", "flags": {}}, {"label": "1056824", "points": [[448, 1117], [1168, 1164], [1165, 1330], [448, 1263]], "group_id": null, "shape_type": "polygon", "flags": {}}, {"label": "1056824", "points": [[454, 1299], [1171, 1367], [1167, 1539], [449, 1544]], "group_id": null, "shape_type": "polygon", "flags": {}}, {"label": "1056824", "points": [[476, 1693], [1203, 1568], [1207, 1753], [475, 1825]], "group_id": null, "shape_type": "polygon", "flags": {}}, {"label": "1056824", "points": [[474, 1850], [1202, 1774], [1207, 2033], [473, 2063]], "group_id": null, "shape_type": "polygon", "flags": {}}, {"label": "1056824", "points": [[471, 2083], [1204, 2053], [1206, 2243], [470, 2244]], "group_id": null, "shape_type": "polygon", "flags": {}}, {"label": "1056824", "points": [[475, 2270], [1206, 2270], [1201, 2569], [471, 2520]], "group_id": null, "shape_type": "polygon", "flags": {}}, {"label": "1056824", "points": [[460, 2544], [1213, 2605], [1206, 2803], [459, 2714]], "group_id": null, "shape_type": "polygon", "flags": {}}], "imagePath": "2ac6ca7c5399845d67e97c74480d293c.jpg", "imageData": null, "imageHeight": 3100, "imageWidth": 1230}