{"version": "", "flags": {}, "shapes": [{"label": "1033458", "points": [[361, 820], [361, 1126], [1148, 1099], [1145, 814]], "group_id": null, "shape_type": "polygon", "flags": {}}, {"label": "1033458", "points": [[405, 1660], [398, 1950], [1153, 1989], [1153, 1713]], "group_id": null, "shape_type": "polygon", "flags": {}}, {"label": "1033459", "points": [[363, 1132], [356, 1456], [1149, 1413], [1144, 1105]], "group_id": null, "shape_type": "polygon", "flags": {}}, {"label": "1033459", "points": [[394, 1956], [382, 2269], [1170, 2288], [1163, 1999]], "group_id": null, "shape_type": "polygon", "flags": {}}, {"label": "1033462", "points": [[355, 1468], [353, 1550], [1155, 1545], [1151, 1423]], "group_id": null, "shape_type": "polygon", "flags": {}}, {"label": "1033462", "points": [[387, 2281], [377, 2480], [1170, 2482], [1177, 2295]], "group_id": null, "shape_type": "polygon", "flags": {}}], "imagePath": "2df57ccb626aaf2cae1e03727b72ebe2.jpg", "imageData": null, "imageHeight": 3100, "imageWidth": 1230}