{"version": "", "flags": {}, "shapes": [{"label": "1056817", "points": [[422, 437], [1186, 400], [1202, 1549], [397, 1551], [413, 796]], "group_id": null, "shape_type": "polygon", "flags": {}}, {"label": "1056817", "points": [[483, 1555], [1229, 1551], [1227, 2963], [455, 2823], [461, 2211]], "group_id": null, "shape_type": "polygon", "flags": {}}, {"label": "1056824", "points": [[443, 955], [1128, 998], [1129, 1239], [437, 1172]], "group_id": null, "shape_type": "polygon", "flags": {}}, {"label": "1056824", "points": [[440, 1194], [1131, 1283], [1131, 1531], [434, 1414]], "group_id": null, "shape_type": "polygon", "flags": {}}, {"label": "1056824", "points": [[445, 922], [1122, 964], [1119, 722], [448, 717]], "group_id": null, "shape_type": "polygon", "flags": {}}, {"label": "1056824", "points": [[449, 689], [1119, 693], [1116, 451], [452, 466]], "group_id": null, "shape_type": "polygon", "flags": {}}, {"label": "1056824", "points": [[505, 1913], [1175, 1830], [1176, 2090], [499, 2123]], "group_id": null, "shape_type": "polygon", "flags": {}}, {"label": "1056824", "points": [[500, 2134], [1179, 2103], [1180, 2355], [496, 2346]], "group_id": null, "shape_type": "polygon", "flags": {}}, {"label": "1056824", "points": [[490, 2364], [1190, 2383], [1223, 2756], [481, 2667]], "group_id": null, "shape_type": "polygon", "flags": {}}, {"label": "1056824", "points": [[504, 1701], [1173, 1578], [1174, 1818], [504, 1906]], "group_id": null, "shape_type": "polygon", "flags": {}}], "imagePath": "36fe61b4ee94efdba948eefb90672c6d.jpg", "imageData": null, "imageHeight": 3100, "imageWidth": 1230}