{"version": "", "flags": {}, "shapes": [{"label": "1033458", "points": [[363, 663], [1171, 670], [1169, 890], [366, 924]], "group_id": null, "shape_type": "polygon", "flags": {}}, {"label": "1033458", "points": [[392, 1549], [553, 1554], [1074, 1722], [1076, 1898], [372, 1720]], "group_id": null, "shape_type": "polygon", "flags": {}}, {"label": "1033459", "points": [[367, 964], [1178, 920], [1177, 1231], [382, 1342]], "group_id": null, "shape_type": "polygon", "flags": {}}, {"label": "1033459", "points": [[375, 1746], [1083, 1926], [1084, 2197], [341, 2080]], "group_id": null, "shape_type": "polygon", "flags": {}}, {"label": "1033462", "points": [[386, 1385], [1188, 1275], [1190, 1549], [388, 1551]], "group_id": null, "shape_type": "polygon", "flags": {}}, {"label": "1033462", "points": [[331, 2103], [1085, 2217], [1084, 2531], [292, 2490]], "group_id": null, "shape_type": "polygon", "flags": {}}], "imagePath": "38d8ed89e755eea2f3346b03c536f4ba.jpg", "imageData": null, "imageHeight": 3100, "imageWidth": 1230}