{"version": "", "flags": {}, "shapes": [{"label": "1033458", "points": [[418, 768], [1142, 782], [1147, 1094], [403, 1086]], "group_id": null, "shape_type": "polygon", "flags": {}}, {"label": "1033459", "points": [[412, 1117], [1141, 1119], [1146, 1273], [402, 1280]], "group_id": null, "shape_type": "polygon", "flags": {}}, {"label": "1033462", "points": [[398, 1307], [1144, 1317], [1154, 1545], [398, 1545]], "group_id": null, "shape_type": "polygon", "flags": {}}, {"label": "1033458", "points": [[439, 1629], [1166, 1631], [1168, 1907], [437, 1902]], "group_id": null, "shape_type": "polygon", "flags": {}}, {"label": "1033459", "points": [[445, 1927], [1170, 1930], [1175, 2074], [448, 2069], [443, 2069]], "group_id": null, "shape_type": "polygon", "flags": {}}, {"label": "1033462", "points": [[437, 2094], [1173, 2099], [1178, 2336], [425, 2346]], "group_id": null, "shape_type": "polygon", "flags": {}}], "imagePath": "41505c312397699556df125cf9cd6c7b.jpg", "imageData": null, "imageHeight": 3100, "imageWidth": 1230}