{"version": "", "flags": {}, "shapes": [{"label": "1056817", "points": [[363, 327], [338, 1545], [1230, 1548], [1226, 380]], "group_id": null, "shape_type": "polygon", "flags": {}}, {"label": "1056817", "points": [[382, 1547], [330, 3021], [1224, 3017], [1228, 1549]], "group_id": null, "shape_type": "polygon", "flags": {}}, {"label": "1056824", "points": [[386, 614], [1168, 647], [1172, 436], [397, 377]], "group_id": null, "shape_type": "polygon", "flags": {}}, {"label": "1056824", "points": [[386, 642], [376, 934], [1160, 951], [1169, 681]], "group_id": null, "shape_type": "polygon", "flags": {}}, {"label": "1056824", "points": [[376, 967], [369, 1268], [1154, 1270], [1161, 982]], "group_id": null, "shape_type": "polygon", "flags": {}}, {"label": "1056824", "points": [[370, 1305], [363, 1548], [1150, 1548], [1154, 1308]], "group_id": null, "shape_type": "polygon", "flags": {}}, {"label": "1056824", "points": [[403, 1774], [1198, 1819], [1212, 1574], [924, 1551], [410, 1544]], "group_id": null, "shape_type": "polygon", "flags": {}}, {"label": "1056824", "points": [[400, 1806], [392, 2073], [1189, 2111], [1198, 1842]], "group_id": null, "shape_type": "polygon", "flags": {}}, {"label": "1056824", "points": [[391, 2100], [378, 2377], [1177, 2401], [1185, 2136]], "group_id": null, "shape_type": "polygon", "flags": {}}, {"label": "1056824", "points": [[380, 2410], [361, 2809], [1165, 2815], [1180, 2435]], "group_id": null, "shape_type": "polygon", "flags": {}}], "imagePath": "435bc3e35e4c4702263f101f46e426f6.jpg", "imageData": null, "imageHeight": 3100, "imageWidth": 1230}