{"version": "", "flags": {}, "shapes": [{"label": "1056817", "points": [[322, 332], [1186, 408], [1206, 1546], [281, 1545]], "group_id": null, "shape_type": "polygon", "flags": {}}, {"label": "1056824", "points": [[344, 401], [334, 594], [1156, 625], [1156, 441]], "group_id": null, "shape_type": "polygon", "flags": {}}, {"label": "1056824", "points": [[336, 619], [333, 846], [1155, 852], [1155, 649]], "group_id": null, "shape_type": "polygon", "flags": {}}, {"label": "1056824", "points": [[330, 874], [325, 1099], [1154, 1079], [1155, 877]], "group_id": null, "shape_type": "polygon", "flags": {}}, {"label": "1056824", "points": [[327, 1132], [320, 1375], [1155, 1321], [1156, 1108]], "group_id": null, "shape_type": "polygon", "flags": {}}, {"label": "1056824", "points": [[1140, 887], [1145, 885], [1145, 885]], "group_id": null, "shape_type": "polygon", "flags": {}}, {"label": "1056824", "points": [[326, 1413], [326, 1544], [1157, 1546], [1156, 1356]], "group_id": null, "shape_type": "polygon", "flags": {}}, {"label": "1056817", "points": [[348, 1547], [1142, 1544], [1164, 2035], [1211, 2986], [257, 3049]], "group_id": null, "shape_type": "polygon", "flags": {}}, {"label": "1056824", "points": [[364, 1548], [363, 1592], [1119, 1685], [1116, 1547]], "group_id": null, "shape_type": "polygon", "flags": {}}, {"label": "1056824", "points": [[365, 1614], [356, 1828], [1122, 1907], [1117, 1714]], "group_id": null, "shape_type": "polygon", "flags": {}}, {"label": "1056824", "points": [[356, 1852], [347, 2046], [1127, 2107], [1124, 1924]], "group_id": null, "shape_type": "polygon", "flags": {}}, {"label": "1056824", "points": [[1123, 1958], [1118, 1956], [1118, 1956]], "group_id": null, "shape_type": "polygon", "flags": {}}, {"label": "1056824", "points": [[343, 2069], [334, 2293], [1121, 2325], [1121, 2127]], "group_id": null, "shape_type": "polygon", "flags": {}}, {"label": "1056824", "points": [[333, 2327], [320, 2574], [1122, 2581], [1126, 2354]], "group_id": null, "shape_type": "polygon", "flags": {}}, {"label": "1056824", "points": [[320, 2607], [304, 2852], [1128, 2846], [1128, 2609]], "group_id": null, "shape_type": "polygon", "flags": {}}, {"label": "1056824", "points": [[303, 2893], [291, 3023], [1171, 2978], [1167, 2879]], "group_id": null, "shape_type": "polygon", "flags": {}}], "imagePath": "43626febc84380feac689be7397b9002.jpg", "imageData": null, "imageHeight": 3100, "imageWidth": 1230}