{"version": "", "flags": {}, "shapes": [{"label": "1033458", "points": [[357, 650], [1165, 696], [1153, 945], [340, 962]], "group_id": null, "shape_type": "polygon", "flags": {}}, {"label": "1033459", "points": [[349, 1011], [1155, 975], [1169, 1304], [332, 1417]], "group_id": null, "shape_type": "polygon", "flags": {}}, {"label": "1033458", "points": [[364, 1545], [359, 1612], [1108, 1799], [1101, 1588], [1009, 1545]], "group_id": null, "shape_type": "polygon", "flags": {}}, {"label": "1033459", "points": [[345, 1641], [1096, 1816], [1096, 2094], [326, 1993]], "group_id": null, "shape_type": "polygon", "flags": {}}], "imagePath": "4734a6fa424dfd85ea390dda18c02afb.jpg", "imageData": null, "imageHeight": 3100, "imageWidth": 1230}