{"version": "", "flags": {}, "shapes": [{"label": "1033458", "points": [[289, 829], [1109, 847], [1103, 1087], [268, 1150]], "group_id": null, "shape_type": "polygon", "flags": {}}, {"label": "1033458", "points": [[310, 1550], [313, 1784], [1094, 1928], [1103, 1718], [442, 1547]], "group_id": null, "shape_type": "polygon", "flags": {}}, {"label": "1033459", "points": [[274, 1199], [1112, 1114], [1112, 1415], [463, 1547], [244, 1547]], "group_id": null, "shape_type": "polygon", "flags": {}}, {"label": "1033459", "points": [[307, 1826], [1106, 1959], [1109, 2238], [301, 2184]], "group_id": null, "shape_type": "polygon", "flags": {}}], "imagePath": "503ab649c8ff7ecf7914703eac7fb100.jpg", "imageData": null, "imageHeight": 3100, "imageWidth": 1230}