{"version": "", "flags": {}, "shapes": [{"label": "1033458", "points": [[370, 767], [366, 1130], [1127, 1090], [1119, 782]], "group_id": null, "shape_type": "polygon", "flags": {}}, {"label": "1033458", "points": [[426, 1559], [414, 1859], [1119, 1901], [1131, 1633]], "group_id": null, "shape_type": "polygon", "flags": {}}, {"label": "1033459", "points": [[357, 1156], [359, 1347], [1140, 1289], [1138, 1118]], "group_id": null, "shape_type": "polygon", "flags": {}}, {"label": "1033459", "points": [[401, 1879], [395, 2042], [1136, 2074], [1132, 1917]], "group_id": null, "shape_type": "polygon", "flags": {}}, {"label": "1033462", "points": [[355, 1379], [363, 1549], [1160, 1549], [1148, 1321]], "group_id": null, "shape_type": "polygon", "flags": {}}, {"label": "1033462", "points": [[391, 2066], [397, 2354], [1148, 2348], [1158, 2094]], "group_id": null, "shape_type": "polygon", "flags": {}}], "imagePath": "53a00089f01488c97634c276acb9b7d5.jpg", "imageData": null, "imageHeight": 3100, "imageWidth": 1230}