{"version": "", "flags": {}, "shapes": [{"label": "1033458", "points": [[467, 655], [1117, 624], [1114, 885], [464, 868]], "group_id": null, "shape_type": "polygon", "flags": {}}, {"label": "1033459", "points": [[464, 919], [1107, 947], [1112, 1108], [462, 1039]], "group_id": null, "shape_type": "polygon", "flags": {}}, {"label": "1033462", "points": [[460, 1106], [1102, 1192], [1102, 1427], [457, 1310]], "group_id": null, "shape_type": "polygon", "flags": {}}, {"label": "1033458", "points": [[478, 1593], [691, 1552], [1132, 1547], [1130, 1681], [473, 1806]], "group_id": null, "shape_type": "polygon", "flags": {}}, {"label": "1033459", "points": [[480, 1837], [1132, 1712], [1135, 1885], [475, 1957]], "group_id": null, "shape_type": "polygon", "flags": {}}, {"label": "1033462", "points": [[475, 2005], [1139, 1933], [1137, 2233], [475, 2228]], "group_id": null, "shape_type": "polygon", "flags": {}}], "imagePath": "5c8e7a9c455469f3b9111d5571acf53d.jpg", "imageData": null, "imageHeight": 3100, "imageWidth": 1230}