{"version": "", "flags": {}, "shapes": [{"label": "1056817", "points": [[421, 427], [1221, 371], [1212, 952], [1197, 1549], [439, 1549], [426, 870]], "group_id": null, "shape_type": "polygon", "flags": {}}, {"label": "1056817", "points": [[436, 1550], [1213, 1550], [1231, 1926], [1231, 3092], [806, 3065], [364, 3025], [393, 2337]], "group_id": null, "shape_type": "polygon", "flags": {}}, {"label": "1056824", "points": [[460, 791], [458, 494], [1151, 483], [1147, 797]], "group_id": null, "shape_type": "polygon", "flags": {}}, {"label": "1056824", "points": [[462, 805], [1149, 812], [1146, 1068], [461, 1023]], "group_id": null, "shape_type": "polygon", "flags": {}}, {"label": "1056824", "points": [[462, 1040], [1146, 1083], [1136, 1337], [461, 1263]], "group_id": null, "shape_type": "polygon", "flags": {}}, {"label": "1056824", "points": [[463, 1278], [1140, 1355], [1145, 1547], [833, 1547], [462, 1484]], "group_id": null, "shape_type": "polygon", "flags": {}}, {"label": "1056824", "points": [[403, 2582], [1202, 2629], [1212, 2993], [386, 2921]], "group_id": null, "shape_type": "polygon", "flags": {}}, {"label": "1056824", "points": [[418, 2296], [1198, 2330], [1200, 2612], [401, 2563]], "group_id": null, "shape_type": "polygon", "flags": {}}, {"label": "1056824", "points": [[434, 2036], [1197, 2053], [1195, 2307], [423, 2279]], "group_id": null, "shape_type": "polygon", "flags": {}}, {"label": "1056824", "points": [[447, 1791], [1187, 1791], [1195, 2036], [436, 2016]], "group_id": null, "shape_type": "polygon", "flags": {}}, {"label": "1056824", "points": [[453, 1776], [1187, 1774], [1178, 1554], [466, 1548]], "group_id": null, "shape_type": "polygon", "flags": {}}], "imagePath": "66f17ae97dd4b6b99667db20153d6111.jpg", "imageData": null, "imageHeight": 3100, "imageWidth": 1230}