{"version": "", "flags": {}, "shapes": [{"label": "1033458", "points": [[349, 510], [341, 727], [1100, 750], [1105, 533]], "group_id": null, "shape_type": "polygon", "flags": {}}, {"label": "1033459", "points": [[340, 756], [338, 1009], [1099, 1021], [1100, 780]], "group_id": null, "shape_type": "polygon", "flags": {}}, {"label": "1033462", "points": [[333, 1043], [324, 1313], [1108, 1309], [1103, 1056]], "group_id": null, "shape_type": "polygon", "flags": {}}, {"label": "1033463", "points": [[324, 1353], [316, 1545], [1103, 1551], [1106, 1342]], "group_id": null, "shape_type": "polygon", "flags": {}}, {"label": "1033458", "points": [[410, 1695], [1169, 1709], [1173, 1551], [414, 1540]], "group_id": null, "shape_type": "polygon", "flags": {}}, {"label": "1033459", "points": [[408, 1718], [399, 1957], [1167, 1969], [1171, 1729]], "group_id": null, "shape_type": "polygon", "flags": {}}, {"label": "1033462", "points": [[394, 1975], [389, 2244], [1169, 2262], [1171, 1989]], "group_id": null, "shape_type": "polygon", "flags": {}}, {"label": "1033463", "points": [[389, 2263], [385, 2648], [1166, 2666], [1171, 2287]], "group_id": null, "shape_type": "polygon", "flags": {}}], "imagePath": "6ae643e799f35b299b6f95c4ed85e8f1.jpg", "imageData": null, "imageHeight": 3100, "imageWidth": 1230}