{"version": "", "flags": {}, "shapes": [{"label": "1056817", "points": [[384, 413], [384, 1547], [1202, 1552], [1199, 396]], "group_id": null, "shape_type": "polygon", "flags": {}}, {"label": "1056824", "points": [[430, 505], [430, 668], [1115, 662], [1112, 478]], "group_id": null, "shape_type": "polygon", "flags": {}}, {"label": "1056824", "points": [[433, 687], [437, 901], [1128, 909], [1120, 681]], "group_id": null, "shape_type": "polygon", "flags": {}}, {"label": "1056824", "points": [[436, 925], [437, 1188], [1126, 1213], [1128, 936]], "group_id": null, "shape_type": "polygon", "flags": {}}, {"label": "1056824", "points": [[438, 1212], [435, 1511], [1130, 1549], [1130, 1236]], "group_id": null, "shape_type": "polygon", "flags": {}}, {"label": "1056817", "points": [[415, 1552], [432, 2942], [1226, 3003], [1233, 1548]], "group_id": null, "shape_type": "polygon", "flags": {}}, {"label": "1056824", "points": [[439, 1609], [447, 1820], [1207, 1762], [1196, 1545], [1036, 1545]], "group_id": null, "shape_type": "polygon", "flags": {}}, {"label": "1056824", "points": [[444, 1838], [447, 2091], [1215, 2064], [1208, 1784]], "group_id": null, "shape_type": "polygon", "flags": {}}, {"label": "1056824", "points": [[447, 2116], [455, 2392], [1211, 2394], [1211, 2089]], "group_id": null, "shape_type": "polygon", "flags": {}}, {"label": "1056824", "points": [[452, 2423], [459, 2786], [1213, 2827], [1213, 2417]], "group_id": null, "shape_type": "polygon", "flags": {}}], "imagePath": "7c312a7a6b19df973130d00acd98ebd2.jpg", "imageData": null, "imageHeight": 3100, "imageWidth": 1230}