{"version": "", "flags": {}, "shapes": [{"label": "1056817", "points": [[349, 487], [349, 487], [349, 487]], "group_id": null, "shape_type": "polygon", "flags": {}}, {"label": "1056824", "points": [[332, 465], [335, 612], [1203, 614], [1202, 477]], "group_id": null, "shape_type": "polygon", "flags": {}}, {"label": "1056824", "points": [[337, 646], [339, 870], [1207, 831], [1205, 645]], "group_id": null, "shape_type": "polygon", "flags": {}}, {"label": "1056817", "points": [[1155, 920], [1155, 920], [1155, 920]], "group_id": null, "shape_type": "polygon", "flags": {}}, {"label": "1056817", "points": [[326, 466], [1217, 471], [1226, 1553], [362, 1546], [344, 1074]], "group_id": null, "shape_type": "polygon", "flags": {}}, {"label": "1056817", "points": [[441, 1168], [440, 1168], [439, 1168]], "group_id": null, "shape_type": "polygon", "flags": {}}, {"label": "1056817", "points": [[375, 1535], [375, 1535], [375, 1535]], "group_id": null, "shape_type": "polygon", "flags": {}}, {"label": "1056824", "points": [[345, 909], [349, 1183], [1209, 1100], [1206, 865]], "group_id": null, "shape_type": "polygon", "flags": {}}, {"label": "1056824", "points": [[351, 920], [349, 915], [349, 915]], "group_id": null, "shape_type": "polygon", "flags": {}}, {"label": "1056824", "points": [[353, 1222], [363, 1529], [434, 1527], [1212, 1404], [1210, 1140]], "group_id": null, "shape_type": "polygon", "flags": {}}, {"label": "1056817", "points": [[389, 1546], [1230, 1552], [1229, 3088], [373, 3090], [372, 2314]], "group_id": null, "shape_type": "polygon", "flags": {}}, {"label": "1056817", "points": [[331, 2280], [331, 2280], [331, 2280]], "group_id": null, "shape_type": "polygon", "flags": {}}, {"label": "1056824", "points": [[414, 1626], [407, 1967], [1227, 1997], [1231, 1687], [897, 1664]], "group_id": null, "shape_type": "polygon", "flags": {}}, {"label": "1056824", "points": [[406, 1997], [398, 2318], [1229, 2323], [1231, 2026], [846, 2011]], "group_id": null, "shape_type": "polygon", "flags": {}}, {"label": "1056824", "points": [[399, 2355], [401, 2674], [1229, 2647], [1229, 2357]], "group_id": null, "shape_type": "polygon", "flags": {}}, {"label": "1056824", "points": [[404, 2362], [404, 2362], [404, 2362]], "group_id": null, "shape_type": "polygon", "flags": {}}, {"label": "1056824", "points": [[402, 2712], [401, 3018], [1233, 2983], [1231, 2688]], "group_id": null, "shape_type": "polygon", "flags": {}}, {"label": "1056824", "points": [[368, 949], [368, 944], [368, 944]], "group_id": null, "shape_type": "polygon", "flags": {}}], "imagePath": "8b693c870ec0bed2a9db869a88aaea87.jpg", "imageData": null, "imageHeight": 3100, "imageWidth": 1230}