{"version": "", "flags": {}, "shapes": [{"label": "1033458", "points": [[342, 827], [317, 1091], [1094, 1079], [1096, 842]], "group_id": null, "shape_type": "polygon", "flags": {}}, {"label": "1033459", "points": [[313, 1141], [294, 1484], [1096, 1405], [1098, 1118]], "group_id": null, "shape_type": "polygon", "flags": {}}, {"label": "1033458", "points": [[369, 1617], [354, 1852], [1092, 1931], [1094, 1723]], "group_id": null, "shape_type": "polygon", "flags": {}}, {"label": "1033459", "points": [[356, 1892], [346, 2200], [1105, 2235], [1096, 1963]], "group_id": null, "shape_type": "polygon", "flags": {}}], "imagePath": "91a054f4b358ec3d1f8dd8709746d2e9.jpg", "imageData": null, "imageHeight": 3100, "imageWidth": 1230}