{"version": "", "flags": {}, "shapes": [{"label": "1033458", "points": [[373, 892], [1171, 868], [1181, 1106], [385, 1163]], "group_id": null, "shape_type": "polygon", "flags": {}}, {"label": "1033459", "points": [[397, 1194], [1186, 1144], [1193, 1408], [435, 1497], [409, 1501]], "group_id": null, "shape_type": "polygon", "flags": {}}, {"label": "1033458", "points": [[423, 1650], [1214, 1686], [1219, 1993], [409, 1984]], "group_id": null, "shape_type": "polygon", "flags": {}}, {"label": "1033459", "points": [[413, 2008], [1210, 2019], [1210, 2317], [411, 2324]], "group_id": null, "shape_type": "polygon", "flags": {}}], "imagePath": "98a25b13a878610a662ad7352e9e6376.jpg", "imageData": null, "imageHeight": 3100, "imageWidth": 1230}