{"version": "", "flags": {}, "shapes": [{"label": "1056817", "points": [[401, 400], [1228, 394], [1230, 1550], [391, 1548], [391, 803]], "group_id": null, "shape_type": "polygon", "flags": {}}, {"label": "1056817", "points": [[439, 1550], [1229, 1550], [1227, 3037], [773, 3037], [398, 2996], [405, 2136]], "group_id": null, "shape_type": "polygon", "flags": {}}, {"label": "1056824", "points": [[433, 455], [1189, 455], [1184, 606], [425, 599]], "group_id": null, "shape_type": "polygon", "flags": {}}, {"label": "1056824", "points": [[427, 625], [1185, 635], [1181, 930], [421, 893]], "group_id": null, "shape_type": "polygon", "flags": {}}, {"label": "1056824", "points": [[425, 928], [1178, 958], [1174, 1245], [424, 1205]], "group_id": null, "shape_type": "polygon", "flags": {}}, {"label": "1056824", "points": [[432, 1235], [1172, 1278], [1183, 1547], [785, 1546], [429, 1517]], "group_id": null, "shape_type": "polygon", "flags": {}}, {"label": "1056824", "points": [[446, 2129], [1231, 2141], [1229, 2478], [436, 2454]], "group_id": null, "shape_type": "polygon", "flags": {}}, {"label": "1056824", "points": [[448, 2105], [1229, 2117], [1229, 1831], [463, 1838]], "group_id": null, "shape_type": "polygon", "flags": {}}, {"label": "1056824", "points": [[439, 2480], [1229, 2504], [1229, 2946], [436, 2913]], "group_id": null, "shape_type": "polygon", "flags": {}}, {"label": "1056824", "points": [[477, 1556], [467, 1804], [1224, 1804], [1231, 1554]], "group_id": null, "shape_type": "polygon", "flags": {}}], "imagePath": "9f94b5364e3f02093c99590c049fea90.jpg", "imageData": null, "imageHeight": 3100, "imageWidth": 1230}