{"version": "", "flags": {}, "shapes": [{"label": "1056817", "points": [[341, 312], [1228, 368], [1228, 1545], [321, 1547], [324, 905]], "group_id": null, "shape_type": "polygon", "flags": {}}, {"label": "1056817", "points": [[345, 1547], [1129, 1546], [1158, 1989], [1177, 2542], [1186, 2916], [262, 2961], [301, 2324], [328, 1851]], "group_id": null, "shape_type": "polygon", "flags": {}}, {"label": "1056824", "points": [[373, 410], [1118, 445], [1121, 653], [363, 632]], "group_id": null, "shape_type": "polygon", "flags": {}}, {"label": "1056824", "points": [[370, 665], [1124, 682], [1124, 884], [363, 882]], "group_id": null, "shape_type": "polygon", "flags": {}}, {"label": "1056824", "points": [[354, 921], [1137, 918], [1148, 1180], [355, 1204]], "group_id": null, "shape_type": "polygon", "flags": {}}, {"label": "1056824", "points": [[361, 1264], [1166, 1238], [1168, 1428], [360, 1494]], "group_id": null, "shape_type": "polygon", "flags": {}}, {"label": "1056824", "points": [[371, 1551], [1086, 1548], [1059, 1716], [371, 1620]], "group_id": null, "shape_type": "polygon", "flags": {}}, {"label": "1056824", "points": [[369, 1660], [1067, 1753], [1069, 1919], [363, 1848]], "group_id": null, "shape_type": "polygon", "flags": {}}, {"label": "1056824", "points": [[361, 1860], [1070, 1925], [1082, 2140], [352, 2104]], "group_id": null, "shape_type": "polygon", "flags": {}}, {"label": "1056824", "points": [[348, 2130], [1112, 2174], [1099, 2405], [337, 2387]], "group_id": null, "shape_type": "polygon", "flags": {}}, {"label": "1056824", "points": [[331, 2423], [1096, 2442], [1093, 2760], [309, 2778]], "group_id": null, "shape_type": "polygon", "flags": {}}], "imagePath": "a3efd5f72c3d7947b9c537014463d27e.jpg", "imageData": null, "imageHeight": 3100, "imageWidth": 1230}