{"version": "", "flags": {}, "shapes": [{"label": "1056817", "points": [[353, 344], [336, 1552], [1206, 1547], [1216, 346]], "group_id": null, "shape_type": "polygon", "flags": {}}, {"label": "1056817", "points": [[353, 1552], [317, 2769], [1189, 2773], [1211, 1551]], "group_id": null, "shape_type": "polygon", "flags": {}}, {"label": "1056824", "points": [[393, 398], [1173, 420], [1170, 548], [394, 522]], "group_id": null, "shape_type": "polygon", "flags": {}}, {"label": "1056824", "points": [[392, 548], [1170, 569], [1173, 711], [390, 697]], "group_id": null, "shape_type": "polygon", "flags": {}}, {"label": "1056824", "points": [[390, 720], [1171, 735], [1170, 973], [387, 967]], "group_id": null, "shape_type": "polygon", "flags": {}}, {"label": "1056824", "points": [[388, 999], [1174, 997], [1176, 1275], [386, 1265]], "group_id": null, "shape_type": "polygon", "flags": {}}, {"label": "1056824", "points": [[385, 1305], [1180, 1313], [1180, 1541], [381, 1536]], "group_id": null, "shape_type": "polygon", "flags": {}}, {"label": "1056824", "points": [[901, 1553], [1144, 1554], [1145, 1677], [389, 1634], [390, 1555]], "group_id": null, "shape_type": "polygon", "flags": {}}, {"label": "1056824", "points": [[389, 1650], [1145, 1694], [1152, 1936], [381, 1904]], "group_id": null, "shape_type": "polygon", "flags": {}}, {"label": "1056824", "points": [[380, 1929], [1154, 1956], [1151, 2216], [375, 2186]], "group_id": null, "shape_type": "polygon", "flags": {}}, {"label": "1056824", "points": [[375, 2216], [1152, 2244], [1148, 2468], [368, 2444]], "group_id": null, "shape_type": "polygon", "flags": {}}, {"label": "1056824", "points": [[364, 2472], [1147, 2498], [1141, 2730], [357, 2715]], "group_id": null, "shape_type": "polygon", "flags": {}}], "imagePath": "a8a045ef61a2d7004fa7d3a66af6b012.jpg", "imageData": null, "imageHeight": 3100, "imageWidth": 1230}