{"version": "", "flags": {}, "shapes": [{"label": "1033458", "points": [[433, 735], [429, 1009], [1150, 1055], [1145, 735]], "group_id": null, "shape_type": "polygon", "flags": {}}, {"label": "1033459", "points": [[429, 1036], [427, 1263], [1147, 1349], [1150, 1090]], "group_id": null, "shape_type": "polygon", "flags": {}}, {"label": "1033462", "points": [[426, 1299], [417, 1544], [1141, 1548], [1148, 1388]], "group_id": null, "shape_type": "polygon", "flags": {}}, {"label": "1033458", "points": [[483, 1730], [474, 1979], [1170, 1940], [1168, 1642]], "group_id": null, "shape_type": "polygon", "flags": {}}, {"label": "1033459", "points": [[471, 1997], [460, 2209], [1176, 2209], [1170, 1961]], "group_id": null, "shape_type": "polygon", "flags": {}}, {"label": "1033462", "points": [[460, 2232], [445, 2472], [1181, 2517], [1176, 2236]], "group_id": null, "shape_type": "polygon", "flags": {}}], "imagePath": "aa28d85a84111d9fd80e1a1e5e92f592.jpg", "imageData": null, "imageHeight": 3100, "imageWidth": 1230}