{"version": "", "flags": {}, "shapes": [{"label": "1056817", "points": [[363, 1549], [369, 876], [372, 301], [1231, 334], [1234, 1548]], "group_id": null, "shape_type": "polygon", "flags": {}}, {"label": "1056817", "points": [[365, 1553], [1233, 1552], [1232, 3021], [700, 3059], [304, 3086], [348, 2164]], "group_id": null, "shape_type": "polygon", "flags": {}}, {"label": "1056824", "points": [[416, 401], [1157, 423], [1162, 659], [411, 640]], "group_id": null, "shape_type": "polygon", "flags": {}}, {"label": "1056824", "points": [[408, 673], [1167, 686], [1168, 964], [405, 960]], "group_id": null, "shape_type": "polygon", "flags": {}}, {"label": "1056824", "points": [[406, 994], [1192, 994], [1192, 1271], [401, 1279]], "group_id": null, "shape_type": "polygon", "flags": {}}, {"label": "1056824", "points": [[407, 1320], [1195, 1310], [1199, 1545], [401, 1550]], "group_id": null, "shape_type": "polygon", "flags": {}}, {"label": "1056824", "points": [[410, 1555], [780, 1555], [1145, 1605], [1137, 1854], [401, 1784]], "group_id": null, "shape_type": "polygon", "flags": {}}, {"label": "1056824", "points": [[403, 1815], [1140, 1874], [1133, 2139], [388, 2087]], "group_id": null, "shape_type": "polygon", "flags": {}}, {"label": "1056824", "points": [[394, 2120], [1137, 2159], [1144, 2443], [379, 2429]], "group_id": null, "shape_type": "polygon", "flags": {}}, {"label": "1056824", "points": [[380, 2458], [1150, 2473], [1143, 2782], [364, 2814]], "group_id": null, "shape_type": "polygon", "flags": {}}], "imagePath": "b80a2ece7accf3bd0dbf015e7da98f09.jpg", "imageData": null, "imageHeight": 3100, "imageWidth": 1230}