{"version": "", "flags": {}, "shapes": [{"label": "1033458", "points": [[429, 575], [1118, 556], [1118, 722], [431, 722]], "group_id": null, "shape_type": "polygon", "flags": {}}, {"label": "1033459", "points": [[434, 738], [1118, 738], [1121, 974], [431, 950]], "group_id": null, "shape_type": "polygon", "flags": {}}, {"label": "1033462", "points": [[429, 977], [1129, 1004], [1146, 1267], [434, 1213]], "group_id": null, "shape_type": "polygon", "flags": {}}, {"label": "1033463", "points": [[433, 1241], [1173, 1300], [1160, 1524], [424, 1442]], "group_id": null, "shape_type": "polygon", "flags": {}}, {"label": "1033458", "points": [[431, 1641], [1116, 1579], [1116, 1731], [431, 1785]], "group_id": null, "shape_type": "polygon", "flags": {}}, {"label": "1033459", "points": [[428, 1795], [1107, 1747], [1117, 1960], [430, 1990]], "group_id": null, "shape_type": "polygon", "flags": {}}, {"label": "1033462", "points": [[431, 2006], [1119, 1982], [1120, 2231], [433, 2234]], "group_id": null, "shape_type": "polygon", "flags": {}}, {"label": "1033463", "points": [[433, 2256], [1146, 2254], [1140, 2466], [433, 2446]], "group_id": null, "shape_type": "polygon", "flags": {}}], "imagePath": "bbfd36286102acfbd73de8e45a2d8501.jpg", "imageData": null, "imageHeight": 3100, "imageWidth": 1230}