{"version": "", "flags": {}, "shapes": [{"label": "1033458", "points": [[359, 803], [1175, 806], [1184, 1120], [359, 1098]], "group_id": null, "shape_type": "polygon", "flags": {}}, {"label": "1033459", "points": [[361, 1168], [1191, 1187], [1182, 1545], [347, 1547]], "group_id": null, "shape_type": "polygon", "flags": {}}, {"label": "1033458", "points": [[400, 1554], [405, 1739], [1206, 1708], [1201, 1552]], "group_id": null, "shape_type": "polygon", "flags": {}}, {"label": "1033459", "points": [[406, 1788], [1202, 1752], [1202, 2193], [403, 2212]], "group_id": null, "shape_type": "polygon", "flags": {}}], "imagePath": "c2c59a0124aceb80086696f1f790e2fa.jpg", "imageData": null, "imageHeight": 3100, "imageWidth": 1230}