{"version": "", "flags": {}, "shapes": [{"label": "1033458", "points": [[504, 518], [1131, 482], [1137, 773], [498, 761]], "group_id": null, "shape_type": "polygon", "flags": {}}, {"label": "1033458", "points": [[534, 1546], [525, 1762], [1173, 1603], [1173, 1546]], "group_id": null, "shape_type": "polygon", "flags": {}}, {"label": "1033459", "points": [[495, 794], [1149, 803], [1152, 1100], [483, 1025]], "group_id": null, "shape_type": "polygon", "flags": {}}, {"label": "1033462", "points": [[474, 1061], [1167, 1160], [1155, 1447], [468, 1271]], "group_id": null, "shape_type": "polygon", "flags": {}}, {"label": "1033463", "points": [[480, 1325], [1173, 1505], [1161, 1547], [459, 1553]], "group_id": null, "shape_type": "polygon", "flags": {}}, {"label": "1033459", "points": [[531, 1784], [1184, 1637], [1179, 1874], [528, 1976]], "group_id": null, "shape_type": "polygon", "flags": {}}, {"label": "1033462", "points": [[528, 1994], [1170, 1904], [1173, 2198], [522, 2213]], "group_id": null, "shape_type": "polygon", "flags": {}}, {"label": "1033463", "points": [[513, 2240], [1187, 2225], [1196, 2530], [504, 2476]], "group_id": null, "shape_type": "polygon", "flags": {}}], "imagePath": "c9b1cfbc2820325ef23b509689f33b02.jpg", "imageData": null, "imageHeight": 3100, "imageWidth": 1230}