{"version": "", "flags": {}, "shapes": [{"label": "1056817", "points": [[356, 396], [1232, 436], [1231, 1551], [327, 1546]], "group_id": null, "shape_type": "polygon", "flags": {}}, {"label": "1056817", "points": [[398, 1553], [1230, 1554], [1228, 3085], [362, 3101]], "group_id": null, "shape_type": "polygon", "flags": {}}, {"label": "1056824", "points": [[399, 460], [1155, 483], [1158, 753], [394, 739]], "group_id": null, "shape_type": "polygon", "flags": {}}, {"label": "1056824", "points": [[388, 773], [1159, 791], [1159, 1087], [384, 1092]], "group_id": null, "shape_type": "polygon", "flags": {}}, {"label": "1056824", "points": [[387, 1133], [1160, 1128], [1162, 1290], [386, 1301]], "group_id": null, "shape_type": "polygon", "flags": {}}, {"label": "1056824", "points": [[395, 1345], [1168, 1333], [1177, 1548], [384, 1541]], "group_id": null, "shape_type": "polygon", "flags": {}}, {"label": "1056824", "points": [[429, 1611], [1182, 1645], [1180, 1924], [425, 1890]], "group_id": null, "shape_type": "polygon", "flags": {}}, {"label": "1056824", "points": [[428, 1923], [1184, 1948], [1182, 2086], [424, 2060]], "group_id": null, "shape_type": "polygon", "flags": {}}, {"label": "1056824", "points": [[429, 2089], [1182, 2110], [1182, 2348], [424, 2339]], "group_id": null, "shape_type": "polygon", "flags": {}}, {"label": "1056824", "points": [[422, 2372], [1227, 2382], [1228, 2633], [418, 2634]], "group_id": null, "shape_type": "polygon", "flags": {}}, {"label": "1056824", "points": [[421, 2666], [1228, 2670], [1225, 2926], [414, 2942]], "group_id": null, "shape_type": "polygon", "flags": {}}], "imagePath": "cfcf10c311ef238e246180433e74d196.jpg", "imageData": null, "imageHeight": 3100, "imageWidth": 1230}