{"version": "", "flags": {}, "shapes": [{"label": "1056817", "points": [[444, 503], [1225, 476], [1220, 1541], [434, 1548]], "group_id": null, "shape_type": "polygon", "flags": {}}, {"label": "1056817", "points": [[383, 1561], [380, 2998], [1222, 3075], [1225, 1538]], "group_id": null, "shape_type": "polygon", "flags": {}}, {"label": "1056824", "points": [[481, 700], [1159, 711], [1161, 521], [485, 536]], "group_id": null, "shape_type": "polygon", "flags": {}}, {"label": "1056824", "points": [[485, 729], [1156, 732], [1153, 910], [484, 877]], "group_id": null, "shape_type": "polygon", "flags": {}}, {"label": "1056824", "points": [[481, 906], [1153, 942], [1140, 1226], [485, 1162]], "group_id": null, "shape_type": "polygon", "flags": {}}, {"label": "1056824", "points": [[479, 1187], [1131, 1265], [1109, 1524], [474, 1407]], "group_id": null, "shape_type": "polygon", "flags": {}}, {"label": "1056824", "points": [[436, 1685], [1093, 1623], [1095, 1784], [435, 1829]], "group_id": null, "shape_type": "polygon", "flags": {}}, {"label": "1056824", "points": [[435, 1855], [1091, 1800], [1120, 2091], [432, 2106]], "group_id": null, "shape_type": "polygon", "flags": {}}, {"label": "1056824", "points": [[438, 2126], [1124, 2113], [1114, 2375], [425, 2359]], "group_id": null, "shape_type": "polygon", "flags": {}}, {"label": "1056824", "points": [[423, 2385], [1120, 2397], [1112, 2685], [420, 2654]], "group_id": null, "shape_type": "polygon", "flags": {}}, {"label": "1056824", "points": [[425, 2684], [1115, 2723], [1133, 2976], [410, 2939]], "group_id": null, "shape_type": "polygon", "flags": {}}], "imagePath": "dfcf0eb5b71de2af832ce56160b25841.jpg", "imageData": null, "imageHeight": 3100, "imageWidth": 1230}