{"version": "", "flags": {}, "shapes": [{"label": "1056817", "points": [[298, 172], [800, 243], [1203, 316], [1205, 985], [1203, 1550], [278, 1550], [288, 628]], "group_id": null, "shape_type": "polygon", "flags": {}}, {"label": "1056824", "points": [[330, 299], [1125, 419], [1121, 672], [326, 642]], "group_id": null, "shape_type": "polygon", "flags": {}}, {"label": "1056824", "points": [[318, 672], [1117, 697], [1116, 972], [315, 1013]], "group_id": null, "shape_type": "polygon", "flags": {}}, {"label": "1056824", "points": [[308, 1053], [1122, 1007], [1119, 1275], [305, 1402]], "group_id": null, "shape_type": "polygon", "flags": {}}, {"label": "1056824", "points": [[316, 1454], [1121, 1314], [1121, 1550], [304, 1550]], "group_id": null, "shape_type": "polygon", "flags": {}}, {"label": "1056817", "points": [[386, 1547], [1229, 1551], [1230, 2984], [337, 3065], [350, 2274]], "group_id": null, "shape_type": "polygon", "flags": {}}, {"label": "1056824", "points": [[444, 1550], [1194, 1554], [1199, 1828], [436, 1737]], "group_id": null, "shape_type": "polygon", "flags": {}}, {"label": "1056824", "points": [[435, 1764], [1200, 1844], [1199, 2142], [416, 2087]], "group_id": null, "shape_type": "polygon", "flags": {}}, {"label": "1056824", "points": [[409, 2117], [1201, 2170], [1197, 2472], [395, 2468]], "group_id": null, "shape_type": "polygon", "flags": {}}, {"label": "1056824", "points": [[394, 2508], [1202, 2505], [1209, 2865], [389, 2929]], "group_id": null, "shape_type": "polygon", "flags": {}}], "imagePath": "e1d6993d38f3644bbf7be98d73580efb.jpg", "imageData": null, "imageHeight": 3100, "imageWidth": 1230}