{"version": "", "flags": {}, "shapes": [{"label": "1056817", "points": [[360, 340], [1197, 364], [1200, 1549], [345, 1546]], "group_id": null, "shape_type": "polygon", "flags": {}}, {"label": "1056824", "points": [[403, 399], [1132, 413], [1135, 707], [403, 698]], "group_id": null, "shape_type": "polygon", "flags": {}}, {"label": "1056824", "points": [[400, 725], [1134, 729], [1134, 995], [394, 994]], "group_id": null, "shape_type": "polygon", "flags": {}}, {"label": "1056824", "points": [[397, 1022], [1140, 1024], [1140, 1287], [391, 1293]], "group_id": null, "shape_type": "polygon", "flags": {}}, {"label": "1056824", "points": [[386, 1328], [1146, 1317], [1149, 1547], [382, 1545]], "group_id": null, "shape_type": "polygon", "flags": {}}, {"label": "1056817", "points": [[428, 1544], [1231, 1552], [1228, 3029], [374, 2981]], "group_id": null, "shape_type": "polygon", "flags": {}}, {"label": "1056824", "points": [[467, 1638], [1189, 1624], [1184, 1875], [458, 1875]], "group_id": null, "shape_type": "polygon", "flags": {}}, {"label": "1056824", "points": [[461, 1896], [1190, 1898], [1187, 2158], [453, 2149]], "group_id": null, "shape_type": "polygon", "flags": {}}, {"label": "1056824", "points": [[444, 2168], [1184, 2184], [1189, 2430], [434, 2402]], "group_id": null, "shape_type": "polygon", "flags": {}}, {"label": "1056824", "points": [[432, 2435], [1202, 2458], [1198, 2642], [426, 2612]], "group_id": null, "shape_type": "polygon", "flags": {}}, {"label": "1056824", "points": [[429, 2640], [1222, 2665], [1215, 2866], [418, 2823]], "group_id": null, "shape_type": "polygon", "flags": {}}], "imagePath": "ed66f718eae49cd4c0ca9973076b807b.jpg", "imageData": null, "imageHeight": 3100, "imageWidth": 1230}