{"version": "", "flags": {}, "shapes": [{"label": "1056817", "points": [[235, 370], [231, 807], [241, 1279], [720, 1279], [718, 362], [483, 366]], "group_id": null, "shape_type": "polygon", "flags": {}}, {"label": "1056817", "points": [[238, 1281], [231, 1612], [231, 2019], [234, 2182], [717, 2195], [718, 1283]], "group_id": null, "shape_type": "polygon", "flags": {}}, {"label": "1056824", "points": [[247, 1963], [709, 1973], [717, 2150], [247, 2145]], "group_id": null, "shape_type": "polygon", "flags": {}}, {"label": "1056824", "points": [[248, 1837], [707, 1840], [709, 1953], [247, 1945]], "group_id": null, "shape_type": "polygon", "flags": {}}, {"label": "1056824", "points": [[247, 1743], [702, 1741], [706, 1820], [248, 1822]], "group_id": null, "shape_type": "polygon", "flags": {}}, {"label": "1056824", "points": [[245, 1601], [710, 1592], [705, 1724], [245, 1726]], "group_id": null, "shape_type": "polygon", "flags": {}}, {"label": "1056824", "points": [[248, 1414], [705, 1420], [709, 1573], [244, 1584]], "group_id": null, "shape_type": "polygon", "flags": {}}, {"label": "1056824", "points": [[251, 1290], [708, 1291], [706, 1402], [249, 1398]], "group_id": null, "shape_type": "polygon", "flags": {}}, {"label": "1056824", "points": [[259, 1089], [716, 1123], [717, 1277], [399, 1278], [260, 1267]], "group_id": null, "shape_type": "polygon", "flags": {}}, {"label": "1056824", "points": [[254, 974], [710, 986], [713, 1084], [255, 1066]], "group_id": null, "shape_type": "polygon", "flags": {}}, {"label": "1056824", "points": [[252, 873], [707, 874], [710, 965], [252, 953]], "group_id": null, "shape_type": "polygon", "flags": {}}, {"label": "1056824", "points": [[252, 725], [707, 739], [708, 856], [255, 848]], "group_id": null, "shape_type": "polygon", "flags": {}}, {"label": "1056824", "points": [[250, 553], [696, 560], [707, 720], [252, 710]], "group_id": null, "shape_type": "polygon", "flags": {}}, {"label": "1056824", "points": [[249, 399], [695, 394], [696, 537], [249, 534]], "group_id": null, "shape_type": "polygon", "flags": {}}], "imagePath": "fbb68959e164e6c6d5bbde1e275ec818.jpg", "imageData": null, "imageHeight": 2560, "imageWidth": 720}