{"version": "", "flags": {}, "shapes": [{"label": "1033458", "points": [[352, 793], [1157, 807], [1152, 1114], [352, 1136]], "group_id": null, "shape_type": "polygon", "flags": {}}, {"label": "1033458", "points": [[379, 1553], [1174, 1584], [1171, 1934], [377, 1883]], "group_id": null, "shape_type": "polygon", "flags": {}}, {"label": "1033459", "points": [[357, 1168], [1159, 1152], [1155, 1444], [360, 1492]], "group_id": null, "shape_type": "polygon", "flags": {}}, {"label": "1033459", "points": [[382, 1912], [1159, 1958], [1160, 2256], [371, 2228]], "group_id": null, "shape_type": "polygon", "flags": {}}], "imagePath": "fe44d36a06e5dcef9fbf1913be2f6a46.jpg", "imageData": null, "imageHeight": 3100, "imageWidth": 1230}