{"version": "", "flags": {}, "shapes": [{"label": "1056817", "points": [[419, 379], [359, 1549], [1228, 1552], [1233, 385]], "group_id": null, "shape_type": "polygon", "flags": {}}, {"label": "1056824", "points": [[462, 445], [446, 692], [1149, 732], [1154, 442]], "group_id": null, "shape_type": "polygon", "flags": {}}, {"label": "1056824", "points": [[448, 711], [438, 985], [1146, 1042], [1149, 759]], "group_id": null, "shape_type": "polygon", "flags": {}}, {"label": "1056824", "points": [[435, 1004], [429, 1267], [1144, 1356], [1146, 1074]], "group_id": null, "shape_type": "polygon", "flags": {}}, {"label": "1056824", "points": [[427, 1288], [414, 1542], [1145, 1547], [1142, 1377]], "group_id": null, "shape_type": "polygon", "flags": {}}, {"label": "1056817", "points": [[400, 1553], [363, 2937], [1211, 2998], [1174, 1553]], "group_id": null, "shape_type": "polygon", "flags": {}}, {"label": "1056824", "points": [[438, 1692], [431, 1936], [1120, 1939], [1123, 1661]], "group_id": null, "shape_type": "polygon", "flags": {}}, {"label": "1056824", "points": [[436, 1953], [432, 2195], [1121, 2212], [1121, 1958]], "group_id": null, "shape_type": "polygon", "flags": {}}, {"label": "1056824", "points": [[436, 2223], [434, 2509], [1115, 2555], [1115, 2233]], "group_id": null, "shape_type": "polygon", "flags": {}}, {"label": "1056824", "points": [[427, 2536], [421, 2845], [1147, 2906], [1137, 2587]], "group_id": null, "shape_type": "polygon", "flags": {}}], "imagePath": "ffeed4500caa70ed335ec1236a408557.jpg", "imageData": null, "imageHeight": 3100, "imageWidth": 1230}